companion_agent/__init__.py
companion_agent/companion_agent.py
companion_agent/frequency_weighted_retriever.py
companion_agent/memory.py
companion_agent/myfaiss.py
companion_agent/profiles.py
companion_agent/run_agent.py
companion_agent/template/0.0 seg_template.txt
companion_agent/template/answer_stylize_template.txt
companion_agent/template/answer_template.txt
companion_agent/template/question_stylize_template.txt
companion_agent/template/seg_template.txt
companion_agent/template/summary_template.txt
companion_agent/template/summary_template_CoN.txt
companion_agent/template/summary_template_CoT.txt
companion_agent/template/summary_template_preview.txt
companion_agent/utils/__init__.py
companion_agent/utils/bm25-wrong.py
companion_agent/utils/bm25.py
companion_agent/utils/chUtil.py
companion_agent/utils/dbjson2json.py
companion_agent/utils/openaitest.py
companion_agent-0.0.5.dist-info/METADATA
companion_agent-0.0.5.dist-info/WHEEL
companion_agent-0.0.5.dist-info/top_level.txt
companion_agent-0.0.5.dist-info/RECORD
