Metadata-Version: 2.1
Name: companion-agent
Version: 0.0.5
Summary: companion agent
Author: cheney
Author-email: cheney23333@qq.com
License: apache 3.0
Requires-Dist: numpy
Requires-Dist: openai
Requires-Dist: langchain
Requires-Dist: langchain-experimental (>=0.0.8)
Requires-Dist: jieba
Requires-Dist: tqdm
Requires-Dist: urwid
Requires-Dist: jsonlines
Requires-Dist: six
Requires-Dist: tiktoken
